yafax/__init__.py
yafax/__main__.py
yafax/cli.py
yafax/core.py
yafax/getseq.py
yafax/index.py
yafax/logger.py
yafax/py.typed
yafax-1.0.0.dist-info/licenses/LICENSE
yafax-1.0.0.dist-info/METADATA
yafax-1.0.0.dist-info/WHEEL
yafax-1.0.0.dist-info/entry_points.txt
yafax-1.0.0.dist-info/top_level.txt
yafax-1.0.0.dist-info/RECORD
