Metadata-Version: 2.4
Name: yafax
Version: 1.0.0
Summary: Yet Another FASTA Index and Sequence Extraction Tool
Author-email: Prosad Kumar Das <sazbio2026@outlook.com>
Maintainer-email: Prosad Kumar Das <sazbio2026@outlook.com>
License-Expression: GPL-3.0-or-later
Project-URL: Homepage, https://github.com/dasprosad/yafax
Project-URL: Repository, https://github.com/dasprosad/yafax
Project-URL: Issues, https://github.com/dasprosad/yafax/issues
Keywords: bioinformatics,genomics,DNA,FASTA,samtools,faidx,sequence,NGS,genome,biology
Classifier: Programming Language :: Python
Classifier: Programming Language :: Python :: 3
Classifier: Programming Language :: Python :: 3 :: Only
Classifier: Operating System :: POSIX
Classifier: Operating System :: Unix
Classifier: Operating System :: MacOS
Classifier: Intended Audience :: Developers
Classifier: Intended Audience :: Science/Research
Classifier: Natural Language :: English
Requires-Python: >=3.11
License-File: LICENSE
Provides-Extra: dev
Requires-Dist: pytest>=9.0; extra == "dev"
Dynamic: license-file
